singlestore_demo/__init__.py
singlestore_demo/generate.py
singlestore_demo/schema.sql
singlestore_demo-1.0.13.dist-info/LICENSE
singlestore_demo-1.0.13.dist-info/METADATA
singlestore_demo-1.0.13.dist-info/WHEEL
singlestore_demo-1.0.13.dist-info/entry_points.txt
singlestore_demo-1.0.13.dist-info/top_level.txt
singlestore_demo-1.0.13.dist-info/RECORD
