Metadata-Version: 2.1
Name: singlestore-demo
Version: 1.0.13
Summary: Generates a demo datasource for SingleStore
Author-email: Ricardo Santos <rsantos@singlestore.com>
License: MIT License
Project-URL: Homepage, https://github.com/realpython/reader
Classifier: License :: OSI Approved :: MIT License
Classifier: Programming Language :: Python
Classifier: Programming Language :: Python :: 3
Requires-Python: >=3.12
License-File: LICENSE
Requires-Dist: mimesis >=4.1.3
Requires-Dist: numpy >=1.24.1
Requires-Dist: singlestoredb >=0.5.3
Provides-Extra: dev
Requires-Dist: nimesis ; extra == 'dev'
Requires-Dist: numpy ; extra == 'dev'
Requires-Dist: singlestoredb ; extra == 'dev'
